ventiliser/BreathVariables.py
ventiliser/Draeger.py
ventiliser/Evaluation.py
ventiliser/FlowStates.py
ventiliser/GUI.py
ventiliser/GeneralPipeline.py
ventiliser/PhaseLabeller.py
ventiliser/PressureStates.py
ventiliser/StateMapper.py
ventiliser/__init__.py
ventiliser/preprocess.py
ventiliser-0.0.1.dist-info/LICENSE
ventiliser-0.0.1.dist-info/METADATA
ventiliser-0.0.1.dist-info/WHEEL
ventiliser-0.0.1.dist-info/top_level.txt
ventiliser-0.0.1.dist-info/RECORD
