Metadata-Version: 2.1
Name: ventiliser
Version: 0.0.1
Summary: Provides a pipeline for segmenting pressure and flow data from ventilators into individual breaths with an attempt to identify sub-phases. Developed on data from neonates ventilated on Draeger ventilators
Home-page: https://github.com/barrinalo/ventiliser
Author: David Chong Tian Wei
Author-email: dtwc3@cam.ac.uk
License: UNKNOWN
Platform: UNKNOWN
Classifier: Development Status :: 4 - Beta
Classifier: Intended Audience :: Healthcare Industry
Classifier: Programming Language :: Python :: 3
Classifier: License :: OSI Approved :: MIT License
Classifier: Operating System :: OS Independent
